<data><event id="0"><start_date>2024-05-15 07:40</start_date><end_date>2024-05-15 08:25</end_date><text>IN-2hW*-Kll</text><kommentar></kommentar><klasse>2hW*</klasse><anzeige></anzeige><rasterid_wp></rasterid_wp><readonly>1</readonly><zimmer>97</zimmer><zimmerkuerzel>H21</zimmerkuerzel><lehrer>-2</lehrer><lehrerkuerzelname>Keller Markus (Kll)</lehrerkuerzelname><lehrer_kurs>Lehrperson aus Kursverbindung  (Kll)</lehrer_kurs><lehrer_rv></lehrer_rv><reservator>Capaul Urs</reservator><reservation></reservation><istrv>1</istrv><markierung>none</markierung><textdeco></textdeco><color>#77B0D4</color><event_type>0_stp</event_type><show_pru_link>0</show_pru_link><show_abs_link>zentral</show_abs_link><show_haa_link>0</show_haa_link><klassentyp>r</klassentyp><lehrerkuerzel>Kll</lehrerkuerzel><kurskuerzel>IN-2hW*-Kll</kurskuerzel><kursid>43802</kursid><kursind></kursind><neuerlehrer></neuerlehrer><mandant></mandant><mandantname></mandantname><info1></info1><anzeigestp></anzeigestp><fachkuerzel>IN</fachkuerzel><history></history><susname></susname><ohnedetails></ohnedetails></event>
<event id="1"><start_date>2024-05-13 07:40</start_date><end_date>2024-05-13 08:25</end_date><text>M-1dNP-Kll</text><kommentar></kommentar><klasse>1dNP</klasse><anzeige></anzeige><rasterid_wp></rasterid_wp><readonly>1</readonly><zimmer>97</zimmer><zimmerkuerzel>H21</zimmerkuerzel><lehrer>-2</lehrer><lehrerkuerzelname>Keller Markus (Kll)</lehrerkuerzelname><lehrer_kurs>Lehrperson aus Kursverbindung  (Kll)</lehrer_kurs><lehrer_rv></lehrer_rv><reservator>Capaul Urs</reservator><reservation></reservation><istrv>1</istrv><markierung>none</markierung><textdeco></textdeco><color>#77B0D4</color><event_type>0_stp</event_type><show_pru_link>0</show_pru_link><show_abs_link>zentral</show_abs_link><show_haa_link>0</show_haa_link><klassentyp>r</klassentyp><lehrerkuerzel>Kll</lehrerkuerzel><kurskuerzel>M-1dNP-Kll</kurskuerzel><kursid>47874</kursid><kursind></kursind><neuerlehrer></neuerlehrer><mandant></mandant><mandantname></mandantname><info1></info1><anzeigestp></anzeigestp><fachkuerzel>M</fachkuerzel><history></history><susname></susname><ohnedetails></ohnedetails></event>
<event id="2"><start_date>2024-05-16 07:40</start_date><end_date>2024-05-16 08:25</end_date><text>M-2gW-Gh</text><kommentar></kommentar><klasse>2gW</klasse><anzeige></anzeige><rasterid_wp></rasterid_wp><readonly>1</readonly><zimmer>97</zimmer><zimmerkuerzel>H21</zimmerkuerzel><lehrer>-2</lehrer><lehrerkuerzelname>Ghobrial Karim (Gh)</lehrerkuerzelname><lehrer_kurs>Lehrperson aus Kursverbindung  (Gh)</lehrer_kurs><lehrer_rv></lehrer_rv><reservator>Capaul Urs</reservator><reservation></reservation><istrv>1</istrv><markierung>none</markierung><textdeco></textdeco><color>#77B0D4</color><event_type>0_stp</event_type><show_pru_link>0</show_pru_link><show_abs_link>zentral</show_abs_link><show_haa_link>0</show_haa_link><klassentyp>r</klassentyp><lehrerkuerzel>Gh</lehrerkuerzel><kurskuerzel>M-2gW-Gh</kurskuerzel><kursid>46036</kursid><kursind></kursind><neuerlehrer></neuerlehrer><mandant></mandant><mandantname></mandantname><info1></info1><anzeigestp></anzeigestp><fachkuerzel>M</fachkuerzel><history></history><susname></susname><ohnedetails></ohnedetails></event>
<event id="3"><start_date>2024-05-14 08:34</start_date><end_date>2024-05-14 09:19</end_date><text>E-2hW*-Sbe</text><kommentar></kommentar><klasse>2hW*</klasse><anzeige></anzeige><rasterid_wp></rasterid_wp><readonly>1</readonly><zimmer>97</zimmer><zimmerkuerzel>H21</zimmerkuerzel><lehrer>-2</lehrer><lehrerkuerzelname>Scharfenberger Judith (Sbe)</lehrerkuerzelname><lehrer_kurs>Lehrperson aus Kursverbindung  (Sbe)</lehrer_kurs><lehrer_rv></lehrer_rv><reservator>Capaul Urs</reservator><reservation></reservation><istrv>1</istrv><markierung>none</markierung><textdeco></textdeco><color>#77B0D4</color><event_type>0_stp</event_type><show_pru_link>0</show_pru_link><show_abs_link>zentral</show_abs_link><show_haa_link>0</show_haa_link><klassentyp>r</klassentyp><lehrerkuerzel>Sbe</lehrerkuerzel><kurskuerzel>E-2hW*-Sbe</kurskuerzel><kursid>43798</kursid><kursind></kursind><neuerlehrer></neuerlehrer><mandant></mandant><mandantname></mandantname><info1></info1><anzeigestp></anzeigestp><fachkuerzel>E</fachkuerzel><history></history><susname></susname><ohnedetails></ohnedetails></event>
<event id="4"><start_date>2024-05-21 08:34</start_date><end_date>2024-05-21 09:19</end_date><text>E-2hW*-Sbe</text><kommentar></kommentar><klasse>2hW*</klasse><anzeige></anzeige><rasterid_wp></rasterid_wp><readonly>1</readonly><zimmer>97</zimmer><zimmerkuerzel>H21</zimmerkuerzel><lehrer>-2</lehrer><lehrerkuerzelname>Scharfenberger Judith (Sbe)</lehrerkuerzelname><lehrer_kurs>Lehrperson aus Kursverbindung  (Sbe)</lehrer_kurs><lehrer_rv></lehrer_rv><reservator>Capaul Urs</reservator><reservation></reservation><istrv>1</istrv><markierung>none</markierung><textdeco></textdeco><color>#77B0D4</color><event_type>0_stp</event_type><show_pru_link>0</show_pru_link><show_abs_link>zentral</show_abs_link><show_haa_link>0</show_haa_link><klassentyp>r</klassentyp><lehrerkuerzel>Sbe</lehrerkuerzel><kurskuerzel>E-2hW*-Sbe</kurskuerzel><kursid>43798</kursid><kursind></kursind><neuerlehrer></neuerlehrer><mandant></mandant><mandantname></mandantname><info1></info1><anzeigestp></anzeigestp><fachkuerzel>E</fachkuerzel><history></history><susname></susname><ohnedetails></ohnedetails></event>
<event id="5"><start_date>2024-05-15 08:34</start_date><end_date>2024-05-15 09:19</end_date><text>IN-2hW*-Kll</text><kommentar></kommentar><klasse>2hW*</klasse><anzeige></anzeige><rasterid_wp></rasterid_wp><readonly>1</readonly><zimmer>97</zimmer><zimmerkuerzel>H21</zimmerkuerzel><lehrer>-2</lehrer><lehrerkuerzelname>Keller Markus (Kll)</lehrerkuerzelname><lehrer_kurs>Lehrperson aus Kursverbindung  (Kll)</lehrer_kurs><lehrer_rv></lehrer_rv><reservator>Capaul Urs</reservator><reservation></reservation><istrv>1</istrv><markierung>none</markierung><textdeco></textdeco><color>#77B0D4</color><event_type>0_stp</event_type><show_pru_link>0</show_pru_link><show_abs_link>zentral</show_abs_link><show_haa_link>0</show_haa_link><klassentyp>r</klassentyp><lehrerkuerzel>Kll</lehrerkuerzel><kurskuerzel>IN-2hW*-Kll</kurskuerzel><kursid>43802</kursid><kursind></kursind><neuerlehrer></neuerlehrer><mandant></mandant><mandantname></mandantname><info1></info1><anzeigestp></anzeigestp><fachkuerzel>IN</fachkuerzel><history></history><susname></susname><ohnedetails></ohnedetails></event>
<event id="6"><start_date>2024-05-13 08:34</start_date><end_date>2024-05-13 09:19</end_date><text>M-1dNP-Kll</text><kommentar></kommentar><klasse>1dNP</klasse><anzeige></anzeige><rasterid_wp></rasterid_wp><readonly>1</readonly><zimmer>97</zimmer><zimmerkuerzel>H21</zimmerkuerzel><lehrer>-2</lehrer><lehrerkuerzelname>Keller Markus (Kll)</lehrerkuerzelname><lehrer_kurs>Lehrperson aus Kursverbindung  (Kll)</lehrer_kurs><lehrer_rv></lehrer_rv><reservator>Capaul Urs</reservator><reservation></reservation><istrv>1</istrv><markierung>none</markierung><textdeco></textdeco><color>#77B0D4</color><event_type>0_stp</event_type><show_pru_link>0</show_pru_link><show_abs_link>zentral</show_abs_link><show_haa_link>0</show_haa_link><klassentyp>r</klassentyp><lehrerkuerzel>Kll</lehrerkuerzel><kurskuerzel>M-1dNP-Kll</kurskuerzel><kursid>47874</kursid><kursind></kursind><neuerlehrer></neuerlehrer><mandant></mandant><mandantname></mandantname><info1></info1><anzeigestp></anzeigestp><fachkuerzel>M</fachkuerzel><history></history><susname></susname><ohnedetails></ohnedetails></event>
<event id="7"><start_date>2024-05-16 08:34</start_date><end_date>2024-05-16 09:19</end_date><text>M-2gW-Gh</text><kommentar></kommentar><klasse>2gW</klasse><anzeige></anzeige><rasterid_wp></rasterid_wp><readonly>1</readonly><zimmer>97</zimmer><zimmerkuerzel>H21</zimmerkuerzel><lehrer>-2</lehrer><lehrerkuerzelname>Ghobrial Karim (Gh)</lehrerkuerzelname><lehrer_kurs>Lehrperson aus Kursverbindung  (Gh)</lehrer_kurs><lehrer_rv></lehrer_rv><reservator>Capaul Urs</reservator><reservation></reservation><istrv>1</istrv><markierung>none</markierung><textdeco></textdeco><color>#77B0D4</color><event_type>0_stp</event_type><show_pru_link>0</show_pru_link><show_abs_link>zentral</show_abs_link><show_haa_link>0</show_haa_link><klassentyp>r</klassentyp><lehrerkuerzel>Gh</lehrerkuerzel><kurskuerzel>M-2gW-Gh</kurskuerzel><kursid>46036</kursid><kursind></kursind><neuerlehrer></neuerlehrer><mandant></mandant><mandantname></mandantname><info1></info1><anzeigestp></anzeigestp><fachkuerzel>M</fachkuerzel><history></history><susname></susname><ohnedetails></ohnedetails></event>
<event id="8"><start_date>2024-05-17 08:34</start_date><end_date>2024-05-17 09:19</end_date><text>sM-2cN**P**-Kll</text><kommentar></kommentar><klasse>2cN**P**</klasse><anzeige></anzeige><rasterid_wp></rasterid_wp><readonly>1</readonly><zimmer>97</zimmer><zimmerkuerzel>H21</zimmerkuerzel><lehrer>-2</lehrer><lehrerkuerzelname>Keller Markus (Kll)</lehrerkuerzelname><lehrer_kurs>Lehrperson aus Kursverbindung  (Kll)</lehrer_kurs><lehrer_rv></lehrer_rv><reservator>Capaul Urs</reservator><reservation></reservation><istrv>1</istrv><markierung>none</markierung><textdeco></textdeco><color>#77B0D4</color><event_type>0_stp</event_type><show_pru_link>0</show_pru_link><show_abs_link>zentral</show_abs_link><show_haa_link>0</show_haa_link><klassentyp>r</klassentyp><lehrerkuerzel>Kll</lehrerkuerzel><kurskuerzel>sM-2cN**P**-Kll</kurskuerzel><kursid>43127</kursid><kursind></kursind><neuerlehrer></neuerlehrer><mandant></mandant><mandantname></mandantname><info1></info1><anzeigestp></anzeigestp><fachkuerzel>sM</fachkuerzel><history></history><susname></susname><ohnedetails></ohnedetails></event>
<event id="9"><start_date>2024-05-14 09:28</start_date><end_date>2024-05-14 10:13</end_date><text>E-1qM*G*-Sbe</text><kommentar></kommentar><klasse>1qM*G*</klasse><anzeige></anzeige><rasterid_wp></rasterid_wp><readonly>1</readonly><zimmer>97</zimmer><zimmerkuerzel>H21</zimmerkuerzel><lehrer>-2</lehrer><lehrerkuerzelname>Scharfenberger Judith (Sbe)</lehrerkuerzelname><lehrer_kurs>Lehrperson aus Kursverbindung  (Sbe)</lehrer_kurs><lehrer_rv></lehrer_rv><reservator>Capaul Urs</reservator><reservation></reservation><istrv>1</istrv><markierung>none</markierung><textdeco></textdeco><color>#77B0D4</color><event_type>0_stp</event_type><show_pru_link>0</show_pru_link><show_abs_link>zentral</show_abs_link><show_haa_link>0</show_haa_link><klassentyp>r</klassentyp><lehrerkuerzel>Sbe</lehrerkuerzel><kurskuerzel>E-1qM*G*-Sbe</kurskuerzel><kursid>51521</kursid><kursind></kursind><neuerlehrer></neuerlehrer><mandant></mandant><mandantname></mandantname><info1></info1><anzeigestp></anzeigestp><fachkuerzel>E</fachkuerzel><history></history><susname></susname><ohnedetails></ohnedetails></event>
<event id="10"><start_date>2024-05-21 09:28</start_date><end_date>2024-05-21 10:13</end_date><text>E-1qM*G*-Sbe</text><kommentar></kommentar><klasse>1qM*G*</klasse><anzeige></anzeige><rasterid_wp></rasterid_wp><readonly>1</readonly><zimmer>97</zimmer><zimmerkuerzel>H21</zimmerkuerzel><lehrer>-2</lehrer><lehrerkuerzelname>Scharfenberger Judith (Sbe)</lehrerkuerzelname><lehrer_kurs>Lehrperson aus Kursverbindung  (Sbe)</lehrer_kurs><lehrer_rv></lehrer_rv><reservator>Capaul Urs</reservator><reservation></reservation><istrv>1</istrv><markierung>none</markierung><textdeco></textdeco><color>#77B0D4</color><event_type>0_stp</event_type><show_pru_link>0</show_pru_link><show_abs_link>zentral</show_abs_link><show_haa_link>0</show_haa_link><klassentyp>r</klassentyp><lehrerkuerzel>Sbe</lehrerkuerzel><kurskuerzel>E-1qM*G*-Sbe</kurskuerzel><kursid>51521</kursid><kursind></kursind><neuerlehrer></neuerlehrer><mandant></mandant><mandantname></mandantname><info1></info1><anzeigestp></anzeigestp><fachkuerzel>E</fachkuerzel><history></history><susname></susname><ohnedetails></ohnedetails></event>
<event id="11"><start_date>2024-05-16 09:28</start_date><end_date>2024-05-16 10:13</end_date><text>M-4aL*M*-Gh</text><kommentar></kommentar><klasse>4aL*M*</klasse><anzeige></anzeige><rasterid_wp></rasterid_wp><readonly>1</readonly><zimmer>97</zimmer><zimmerkuerzel>H21</zimmerkuerzel><lehrer>-2</lehrer><lehrerkuerzelname>Ghobrial Karim (Gh)</lehrerkuerzelname><lehrer_kurs>Lehrperson aus Kursverbindung  (Gh)</lehrer_kurs><lehrer_rv></lehrer_rv><reservator>Capaul Urs</reservator><reservation></reservation><istrv>1</istrv><markierung>none</markierung><textdeco></textdeco><color>#77B0D4</color><event_type>0_stp</event_type><show_pru_link>0</show_pru_link><show_abs_link>zentral</show_abs_link><show_haa_link>0</show_haa_link><klassentyp>r</klassentyp><lehrerkuerzel>Gh</lehrerkuerzel><kurskuerzel>M-4aL*M*-Gh</kurskuerzel><kursid>34160</kursid><kursind></kursind><neuerlehrer></neuerlehrer><mandant></mandant><mandantname></mandantname><info1></info1><anzeigestp></anzeigestp><fachkuerzel>M</fachkuerzel><history></history><susname></susname><ohnedetails></ohnedetails></event>
<event id="12"><start_date>2024-05-15 09:28</start_date><end_date>2024-05-15 10:13</end_date><text>M-4bLM-Hch</text><kommentar></kommentar><klasse>4bLM</klasse><anzeige></anzeige><rasterid_wp></rasterid_wp><readonly>1</readonly><zimmer>97</zimmer><zimmerkuerzel>H21</zimmerkuerzel><lehrer>-2</lehrer><lehrerkuerzelname>Heydenreich Martin (Hch)</lehrerkuerzelname><lehrer_kurs>Lehrperson aus Kursverbindung  (Hch)</lehrer_kurs><lehrer_rv></lehrer_rv><reservator>Capaul Urs</reservator><reservation></reservation><istrv>1</istrv><markierung>none</markierung><textdeco></textdeco><color>#77B0D4</color><event_type>0_stp</event_type><show_pru_link>0</show_pru_link><show_abs_link>zentral</show_abs_link><show_haa_link>0</show_haa_link><klassentyp>r</klassentyp><lehrerkuerzel>Hch</lehrerkuerzel><kurskuerzel>M-4bLM-Hch</kurskuerzel><kursid>34287</kursid><kursind></kursind><neuerlehrer></neuerlehrer><mandant></mandant><mandantname></mandantname><info1></info1><anzeigestp></anzeigestp><fachkuerzel>M</fachkuerzel><history></history><susname></susname><ohnedetails></ohnedetails></event>
<event id="13"><start_date>2024-05-17 09:28</start_date><end_date>2024-05-17 10:13</end_date><text>M-4mS*-Kll</text><kommentar></kommentar><klasse>4mS*</klasse><anzeige></anzeige><rasterid_wp></rasterid_wp><readonly>1</readonly><zimmer>97</zimmer><zimmerkuerzel>H21</zimmerkuerzel><lehrer>-2</lehrer><lehrerkuerzelname>Keller Markus (Kll)</lehrerkuerzelname><lehrer_kurs>Lehrperson aus Kursverbindung  (Kll)</lehrer_kurs><lehrer_rv></lehrer_rv><reservator>Capaul Urs</reservator><reservation></reservation><istrv>1</istrv><markierung>none</markierung><textdeco></textdeco><color>#77B0D4</color><event_type>0_stp</event_type><show_pru_link>0</show_pru_link><show_abs_link>zentral</show_abs_link><show_haa_link>0</show_haa_link><klassentyp>r</klassentyp><lehrerkuerzel>Kll</lehrerkuerzel><kurskuerzel>M-4mS*-Kll</kurskuerzel><kursid>36995</kursid><kursind></kursind><neuerlehrer></neuerlehrer><mandant></mandant><mandantname></mandantname><info1></info1><anzeigestp></anzeigestp><fachkuerzel>M</fachkuerzel><history></history><susname></susname><ohnedetails></ohnedetails></event>
<event id="14"><start_date>2024-05-13 09:28</start_date><end_date>2024-05-13 10:13</end_date><text>sM-1gNP-Snr</text><kommentar></kommentar><klasse>1gNP</klasse><anzeige></anzeige><rasterid_wp></rasterid_wp><readonly>1</readonly><zimmer>97</zimmer><zimmerkuerzel>H21</zimmerkuerzel><lehrer>-2</lehrer><lehrerkuerzelname>Schn&#252;rer Olaf (Snr)</lehrerkuerzelname><lehrer_kurs>Lehrperson aus Kursverbindung  (Snr)</lehrer_kurs><lehrer_rv></lehrer_rv><reservator>Capaul Urs</reservator><reservation></reservation><istrv>1</istrv><markierung>none</markierung><textdeco></textdeco><color>#77B0D4</color><event_type>0_stp</event_type><show_pru_link>0</show_pru_link><show_abs_link>zentral</show_abs_link><show_haa_link>0</show_haa_link><klassentyp>r</klassentyp><lehrerkuerzel>Snr</lehrerkuerzel><kurskuerzel>sM-1gNP-Snr</kurskuerzel><kursid>50811</kursid><kursind></kursind><neuerlehrer></neuerlehrer><mandant></mandant><mandantname></mandantname><info1></info1><anzeigestp></anzeigestp><fachkuerzel>sM</fachkuerzel><history></history><susname></susname><ohnedetails></ohnedetails></event>
<event id="15"><start_date>2024-05-14 10:30</start_date><end_date>2024-05-14 11:15</end_date><text>IN-4bLM-Kll</text><kommentar></kommentar><klasse>4bLM</klasse><anzeige></anzeige><rasterid_wp></rasterid_wp><readonly>1</readonly><zimmer>97</zimmer><zimmerkuerzel>H21</zimmerkuerzel><lehrer>-2</lehrer><lehrerkuerzelname>Keller Markus (Kll)</lehrerkuerzelname><lehrer_kurs>Lehrperson aus Kursverbindung  (Kll)</lehrer_kurs><lehrer_rv></lehrer_rv><reservator>Capaul Urs</reservator><reservation></reservation><istrv>1</istrv><markierung>none</markierung><textdeco></textdeco><color>#77B0D4</color><event_type>0_stp</event_type><show_pru_link>0</show_pru_link><show_abs_link>zentral</show_abs_link><show_haa_link>0</show_haa_link><klassentyp>r</klassentyp><lehrerkuerzel>Kll</lehrerkuerzel><kurskuerzel>IN-4bLM-Kll</kurskuerzel><kursid>34294</kursid><kursind></kursind><neuerlehrer></neuerlehrer><mandant></mandant><mandantname></mandantname><info1></info1><anzeigestp></anzeigestp><fachkuerzel>IN</fachkuerzel><history></history><susname></susname><ohnedetails></ohnedetails></event>
<event id="16"><start_date>2024-05-21 10:30</start_date><end_date>2024-05-21 11:15</end_date><text>IN-4bLM-Kll</text><kommentar></kommentar><klasse>4bLM</klasse><anzeige></anzeige><rasterid_wp></rasterid_wp><readonly>1</readonly><zimmer>97</zimmer><zimmerkuerzel>H21</zimmerkuerzel><lehrer>-2</lehrer><lehrerkuerzelname>Keller Markus (Kll)</lehrerkuerzelname><lehrer_kurs>Lehrperson aus Kursverbindung  (Kll)</lehrer_kurs><lehrer_rv></lehrer_rv><reservator>Capaul Urs</reservator><reservation></reservation><istrv>1</istrv><markierung>none</markierung><textdeco></textdeco><color>#77B0D4</color><event_type>0_stp</event_type><show_pru_link>0</show_pru_link><show_abs_link>zentral</show_abs_link><show_haa_link>0</show_haa_link><klassentyp>r</klassentyp><lehrerkuerzel>Kll</lehrerkuerzel><kurskuerzel>IN-4bLM-Kll</kurskuerzel><kursid>34294</kursid><kursind></kursind><neuerlehrer></neuerlehrer><mandant></mandant><mandantname></mandantname><info1></info1><anzeigestp></anzeigestp><fachkuerzel>IN</fachkuerzel><history></history><susname></susname><ohnedetails></ohnedetails></event>
<event id="17"><start_date>2024-05-16 10:30</start_date><end_date>2024-05-16 11:15</end_date><text>M-2hW*-Gh</text><kommentar></kommentar><klasse>2hW*</klasse><anzeige></anzeige><rasterid_wp></rasterid_wp><readonly>1</readonly><zimmer>97</zimmer><zimmerkuerzel>H21</zimmerkuerzel><lehrer>-2</lehrer><lehrerkuerzelname>Ghobrial Karim (Gh)</lehrerkuerzelname><lehrer_kurs>Lehrperson aus Kursverbindung  (Gh)</lehrer_kurs><lehrer_rv></lehrer_rv><reservator>Capaul Urs</reservator><reservation></reservation><istrv>1</istrv><markierung>none</markierung><textdeco></textdeco><color>#77B0D4</color><event_type>0_stp</event_type><show_pru_link>0</show_pru_link><show_abs_link>zentral</show_abs_link><show_haa_link>0</show_haa_link><klassentyp>r</klassentyp><lehrerkuerzel>Gh</lehrerkuerzel><kurskuerzel>M-2hW*-Gh</kurskuerzel><kursid>43804</kursid><kursind></kursind><neuerlehrer></neuerlehrer><mandant></mandant><mandantname></mandantname><info1></info1><anzeigestp></anzeigestp><fachkuerzel>M</fachkuerzel><history></history><susname></susname><ohnedetails></ohnedetails></event>
<event id="18"><start_date>2024-05-15 10:30</start_date><end_date>2024-05-15 11:15</end_date><text>M-4bLM-Hch</text><kommentar></kommentar><klasse>4bLM</klasse><anzeige></anzeige><rasterid_wp></rasterid_wp><readonly>1</readonly><zimmer>97</zimmer><zimmerkuerzel>H21</zimmerkuerzel><lehrer>-2</lehrer><lehrerkuerzelname>Heydenreich Martin (Hch)</lehrerkuerzelname><lehrer_kurs>Lehrperson aus Kursverbindung  (Hch)</lehrer_kurs><lehrer_rv></lehrer_rv><reservator>Capaul Urs</reservator><reservation></reservation><istrv>1</istrv><markierung>none</markierung><textdeco></textdeco><color>#77B0D4</color><event_type>0_stp</event_type><show_pru_link>0</show_pru_link><show_abs_link>zentral</show_abs_link><show_haa_link>0</show_haa_link><klassentyp>r</klassentyp><lehrerkuerzel>Hch</lehrerkuerzel><kurskuerzel>M-4bLM-Hch</kurskuerzel><kursid>34287</kursid><kursind></kursind><neuerlehrer></neuerlehrer><mandant></mandant><mandantname></mandantname><info1></info1><anzeigestp></anzeigestp><fachkuerzel>M</fachkuerzel><history></history><susname></susname><ohnedetails></ohnedetails></event>
<event id="19"><start_date>2024-05-17 10:30</start_date><end_date>2024-05-17 11:15</end_date><text>M-4mS*-Kll</text><kommentar></kommentar><klasse>4mS*</klasse><anzeige></anzeige><rasterid_wp></rasterid_wp><readonly>1</readonly><zimmer>97</zimmer><zimmerkuerzel>H21</zimmerkuerzel><lehrer>-2</lehrer><lehrerkuerzelname>Keller Markus (Kll)</lehrerkuerzelname><lehrer_kurs>Lehrperson aus Kursverbindung  (Kll)</lehrer_kurs><lehrer_rv></lehrer_rv><reservator>Capaul Urs</reservator><reservation></reservation><istrv>1</istrv><markierung>none</markierung><textdeco></textdeco><color>#77B0D4</color><event_type>0_stp</event_type><show_pru_link>0</show_pru_link><show_abs_link>zentral</show_abs_link><show_haa_link>0</show_haa_link><klassentyp>r</klassentyp><lehrerkuerzel>Kll</lehrerkuerzel><kurskuerzel>M-4mS*-Kll</kurskuerzel><kursid>36995</kursid><kursind></kursind><neuerlehrer></neuerlehrer><mandant></mandant><mandantname></mandantname><info1></info1><anzeigestp></anzeigestp><fachkuerzel>M</fachkuerzel><history></history><susname></susname><ohnedetails></ohnedetails></event>
<event id="20"><start_date>2024-05-13 10:30</start_date><end_date>2024-05-13 11:15</end_date><text>sM-2cN**P**-Kll</text><kommentar></kommentar><klasse>2cN**P**</klasse><anzeige></anzeige><rasterid_wp></rasterid_wp><readonly>1</readonly><zimmer>97</zimmer><zimmerkuerzel>H21</zimmerkuerzel><lehrer>-2</lehrer><lehrerkuerzelname>Keller Markus (Kll)</lehrerkuerzelname><lehrer_kurs>Lehrperson aus Kursverbindung  (Kll)</lehrer_kurs><lehrer_rv></lehrer_rv><reservator>Capaul Urs</reservator><reservation></reservation><istrv>1</istrv><markierung>none</markierung><textdeco></textdeco><color>#77B0D4</color><event_type>0_stp</event_type><show_pru_link>0</show_pru_link><show_abs_link>zentral</show_abs_link><show_haa_link>0</show_haa_link><klassentyp>r</klassentyp><lehrerkuerzel>Kll</lehrerkuerzel><kurskuerzel>sM-2cN**P**-Kll</kurskuerzel><kursid>43127</kursid><kursind></kursind><neuerlehrer></neuerlehrer><mandant></mandant><mandantname></mandantname><info1></info1><anzeigestp></anzeigestp><fachkuerzel>sM</fachkuerzel><history></history><susname></susname><ohnedetails></ohnedetails></event>
<event id="21"><start_date>2024-05-14 11:24</start_date><end_date>2024-05-14 12:09</end_date><text>IN-4bLM-Kll</text><kommentar></kommentar><klasse>4bLM</klasse><anzeige></anzeige><rasterid_wp></rasterid_wp><readonly>1</readonly><zimmer>97</zimmer><zimmerkuerzel>H21</zimmerkuerzel><lehrer>-2</lehrer><lehrerkuerzelname>Keller Markus (Kll)</lehrerkuerzelname><lehrer_kurs>Lehrperson aus Kursverbindung  (Kll)</lehrer_kurs><lehrer_rv></lehrer_rv><reservator>Capaul Urs</reservator><reservation></reservation><istrv>1</istrv><markierung>none</markierung><textdeco></textdeco><color>#77B0D4</color><event_type>0_stp</event_type><show_pru_link>0</show_pru_link><show_abs_link>zentral</show_abs_link><show_haa_link>0</show_haa_link><klassentyp>r</klassentyp><lehrerkuerzel>Kll</lehrerkuerzel><kurskuerzel>IN-4bLM-Kll</kurskuerzel><kursid>34294</kursid><kursind></kursind><neuerlehrer></neuerlehrer><mandant></mandant><mandantname></mandantname><info1></info1><anzeigestp></anzeigestp><fachkuerzel>IN</fachkuerzel><history></history><susname></susname><ohnedetails></ohnedetails></event>
<event id="22"><start_date>2024-05-21 11:24</start_date><end_date>2024-05-21 12:09</end_date><text>IN-4bLM-Kll</text><kommentar></kommentar><klasse>4bLM</klasse><anzeige></anzeige><rasterid_wp></rasterid_wp><readonly>1</readonly><zimmer>97</zimmer><zimmerkuerzel>H21</zimmerkuerzel><lehrer>-2</lehrer><lehrerkuerzelname>Keller Markus (Kll)</lehrerkuerzelname><lehrer_kurs>Lehrperson aus Kursverbindung  (Kll)</lehrer_kurs><lehrer_rv></lehrer_rv><reservator>Capaul Urs</reservator><reservation></reservation><istrv>1</istrv><markierung>none</markierung><textdeco></textdeco><color>#77B0D4</color><event_type>0_stp</event_type><show_pru_link>0</show_pru_link><show_abs_link>zentral</show_abs_link><show_haa_link>0</show_haa_link><klassentyp>r</klassentyp><lehrerkuerzel>Kll</lehrerkuerzel><kurskuerzel>IN-4bLM-Kll</kurskuerzel><kursid>34294</kursid><kursind></kursind><neuerlehrer></neuerlehrer><mandant></mandant><mandantname></mandantname><info1></info1><anzeigestp></anzeigestp><fachkuerzel>IN</fachkuerzel><history></history><susname></susname><ohnedetails></ohnedetails></event>
<event id="23"><start_date>2024-05-16 11:24</start_date><end_date>2024-05-16 12:09</end_date><text>M-2hW*-Gh</text><kommentar></kommentar><klasse>2hW*</klasse><anzeige></anzeige><rasterid_wp></rasterid_wp><readonly>1</readonly><zimmer>97</zimmer><zimmerkuerzel>H21</zimmerkuerzel><lehrer>-2</lehrer><lehrerkuerzelname>Ghobrial Karim (Gh)</lehrerkuerzelname><lehrer_kurs>Lehrperson aus Kursverbindung  (Gh)</lehrer_kurs><lehrer_rv></lehrer_rv><reservator>Capaul Urs</reservator><reservation></reservation><istrv>1</istrv><markierung>none</markierung><textdeco></textdeco><color>#77B0D4</color><event_type>0_stp</event_type><show_pru_link>0</show_pru_link><show_abs_link>zentral</show_abs_link><show_haa_link>0</show_haa_link><klassentyp>r</klassentyp><lehrerkuerzel>Gh</lehrerkuerzel><kurskuerzel>M-2hW*-Gh</kurskuerzel><kursid>43804</kursid><kursind></kursind><neuerlehrer></neuerlehrer><mandant></mandant><mandantname></mandantname><info1></info1><anzeigestp></anzeigestp><fachkuerzel>M</fachkuerzel><history></history><susname></susname><ohnedetails></ohnedetails></event>
<event id="24"><start_date>2024-05-17 11:24</start_date><end_date>2024-05-17 12:09</end_date><text>Nachpr&#252;fung</text><kommentar></kommentar><klasse></klasse><anzeige></anzeige><rasterid_wp></rasterid_wp><readonly>1</readonly><zimmer>97</zimmer><zimmerkuerzel>H21</zimmerkuerzel><lehrer>-2</lehrer><lehrerkuerzelname></lehrerkuerzelname><lehrer_kurs>Ohne Lehrpersonenverbindung</lehrer_kurs><lehrer_rv></lehrer_rv><reservator>Thommen Deborah</reservator><reservation>1</reservation><istrv>1</istrv><markierung>none</markierung><textdeco></textdeco><color>#77B0D4</color><event_type>0_stp</event_type><show_pru_link>0</show_pru_link><show_abs_link>zentral</show_abs_link><show_haa_link>0</show_haa_link><klassentyp></klassentyp><lehrerkuerzel></lehrerkuerzel><kurskuerzel>Reserviert</kurskuerzel><kursid></kursid><kursind></kursind><neuerlehrer></neuerlehrer><mandant></mandant><mandantname></mandantname><info1></info1><anzeigestp>Nachpr&#252;fung</anzeigestp><fachkuerzel></fachkuerzel><history></history><susname></susname><ohnedetails></ohnedetails></event>
<event id="25"><start_date>2024-05-13 11:24</start_date><end_date>2024-05-13 12:09</end_date><text>sM-2cN**P**-Kll</text><kommentar></kommentar><klasse>2cN**P**</klasse><anzeige></anzeige><rasterid_wp></rasterid_wp><readonly>1</readonly><zimmer>97</zimmer><zimmerkuerzel>H21</zimmerkuerzel><lehrer>-2</lehrer><lehrerkuerzelname>Keller Markus (Kll)</lehrerkuerzelname><lehrer_kurs>Lehrperson aus Kursverbindung  (Kll)</lehrer_kurs><lehrer_rv></lehrer_rv><reservator>Capaul Urs</reservator><reservation></reservation><istrv>1</istrv><markierung>none</markierung><textdeco></textdeco><color>#77B0D4</color><event_type>0_stp</event_type><show_pru_link>0</show_pru_link><show_abs_link>zentral</show_abs_link><show_haa_link>0</show_haa_link><klassentyp>r</klassentyp><lehrerkuerzel>Kll</lehrerkuerzel><kurskuerzel>sM-2cN**P**-Kll</kurskuerzel><kursid>43127</kursid><kursind></kursind><neuerlehrer></neuerlehrer><mandant></mandant><mandantname></mandantname><info1></info1><anzeigestp></anzeigestp><fachkuerzel>sM</fachkuerzel><history></history><susname></susname><ohnedetails></ohnedetails></event>
<event id="26"><start_date>2024-05-15 11:24</start_date><end_date>2024-05-15 12:09</end_date><text>sM-3**^d^P-Cc</text><kommentar></kommentar><klasse>3cN**P**,3dNP</klasse><anzeige></anzeige><rasterid_wp></rasterid_wp><readonly>1</readonly><zimmer>97</zimmer><zimmerkuerzel>H21</zimmerkuerzel><lehrer>-2</lehrer><lehrerkuerzelname>Cincera Manuela (Cc)</lehrerkuerzelname><lehrer_kurs>Lehrperson aus Kursverbindung  (Cc)</lehrer_kurs><lehrer_rv></lehrer_rv><reservator>Capaul Urs</reservator><reservation></reservation><istrv>1</istrv><markierung>moved</markierung><textdeco></textdeco><color>#fdff5b</color><event_type>0_stp</event_type><show_pru_link>0</show_pru_link><show_abs_link>zentral</show_abs_link><show_haa_link>0</show_haa_link><klassentyp>r</klassentyp><lehrerkuerzel>Cc</lehrerkuerzel><kurskuerzel>sM-3**^d^P-Cc</kurskuerzel><kursid>38481</kursid><kursind></kursind><neuerlehrer></neuerlehrer><mandant></mandant><mandantname></mandantname><info1></info1><anzeigestp></anzeigestp><fachkuerzel>sM</fachkuerzel><history></history><susname></susname><ohnedetails></ohnedetails></event>
<event id="27"><start_date>2024-05-17 12:14</start_date><end_date>2024-05-17 12:59</end_date><text>FF261.2</text><kommentar></kommentar><klasse>FF261.2</klasse><anzeige></anzeige><rasterid_wp></rasterid_wp><readonly>1</readonly><zimmer>97</zimmer><zimmerkuerzel>H21</zimmerkuerzel><lehrer>-2</lehrer><lehrerkuerzelname>Bl&#246;chliger Ivo (Blc)</lehrerkuerzelname><lehrer_kurs>Lehrperson aus Kursverbindung  (Blc)</lehrer_kurs><lehrer_rv></lehrer_rv><reservator>Capaul Urs</reservator><reservation></reservation><istrv>1</istrv><markierung>none</markierung><textdeco></textdeco><color>#77B0D4</color><event_type>0_stp</event_type><show_pru_link>1</show_pru_link><show_abs_link>zentral</show_abs_link><show_haa_link>1</show_haa_link><klassentyp>v</klassentyp><lehrerkuerzel>Blc</lehrerkuerzel><kurskuerzel>FF261.2</kurskuerzel><kursid>49536</kursid><kursind>1</kursind><neuerlehrer></neuerlehrer><mandant></mandant><mandantname></mandantname><info1></info1><anzeigestp></anzeigestp><fachkuerzel>IN</fachkuerzel><history></history><susname></susname><ohnedetails></ohnedetails></event>
<event id="28"><start_date>2024-05-17 13:04</start_date><end_date>2024-05-17 13:49</end_date><text>FF261.2</text><kommentar></kommentar><klasse>FF261.2</klasse><anzeige></anzeige><rasterid_wp></rasterid_wp><readonly>1</readonly><zimmer>97</zimmer><zimmerkuerzel>H21</zimmerkuerzel><lehrer>-2</lehrer><lehrerkuerzelname>Bl&#246;chliger Ivo (Blc)</lehrerkuerzelname><lehrer_kurs>Lehrperson aus Kursverbindung  (Blc)</lehrer_kurs><lehrer_rv></lehrer_rv><reservator>Capaul Urs</reservator><reservation></reservation><istrv>1</istrv><markierung>none</markierung><textdeco></textdeco><color>#77B0D4</color><event_type>0_stp</event_type><show_pru_link>1</show_pru_link><show_abs_link>zentral</show_abs_link><show_haa_link>1</show_haa_link><klassentyp>v</klassentyp><lehrerkuerzel>Blc</lehrerkuerzel><kurskuerzel>FF261.2</kurskuerzel><kursid>49536</kursid><kursind>1</kursind><neuerlehrer></neuerlehrer><mandant></mandant><mandantname></mandantname><info1></info1><anzeigestp></anzeigestp><fachkuerzel>IN</fachkuerzel><history></history><susname></susname><ohnedetails></ohnedetails></event>
<event id="29"><start_date>2024-05-16 13:04</start_date><end_date>2024-05-16 13:49</end_date><text>M-4lW-Gh</text><kommentar></kommentar><klasse>4lW</klasse><anzeige></anzeige><rasterid_wp></rasterid_wp><readonly>1</readonly><zimmer>97</zimmer><zimmerkuerzel>H21</zimmerkuerzel><lehrer>-2</lehrer><lehrerkuerzelname>Ghobrial Karim (Gh)</lehrerkuerzelname><lehrer_kurs>Lehrperson aus Kursverbindung  (Gh)</lehrer_kurs><lehrer_rv></lehrer_rv><reservator>Capaul Urs</reservator><reservation></reservation><istrv>1</istrv><markierung>none</markierung><textdeco></textdeco><color>#77B0D4</color><event_type>0_stp</event_type><show_pru_link>0</show_pru_link><show_abs_link>zentral</show_abs_link><show_haa_link>0</show_haa_link><klassentyp>r</klassentyp><lehrerkuerzel>Gh</lehrerkuerzel><kurskuerzel>M-4lW-Gh</kurskuerzel><kursid>36882</kursid><kursind></kursind><neuerlehrer></neuerlehrer><mandant></mandant><mandantname></mandantname><info1></info1><anzeigestp></anzeigestp><fachkuerzel>M</fachkuerzel><history></history><susname></susname><ohnedetails></ohnedetails></event>
<event id="30"><start_date>2024-05-14 13:55</start_date><end_date>2024-05-14 14:40</end_date><text>EF05a</text><kommentar></kommentar><klasse>EF05a</klasse><anzeige></anzeige><rasterid_wp></rasterid_wp><readonly>1</readonly><zimmer>97</zimmer><zimmerkuerzel>H21</zimmerkuerzel><lehrer>-2</lehrer><lehrerkuerzelname>Bl&#246;chliger Ivo (Blc)</lehrerkuerzelname><lehrer_kurs>Lehrperson aus Kursverbindung  (Blc)</lehrer_kurs><lehrer_rv></lehrer_rv><reservator>Capaul Urs</reservator><reservation></reservation><istrv>1</istrv><markierung>none</markierung><textdeco></textdeco><color>#77B0D4</color><event_type>0_stp</event_type><show_pru_link>1</show_pru_link><show_abs_link>zentral</show_abs_link><show_haa_link>1</show_haa_link><klassentyp>v</klassentyp><lehrerkuerzel>Blc</lehrerkuerzel><kurskuerzel>EF05a</kurskuerzel><kursid>49964</kursid><kursind>0</kursind><neuerlehrer></neuerlehrer><mandant></mandant><mandantname></mandantname><info1></info1><anzeigestp></anzeigestp><fachkuerzel>IN</fachkuerzel><history></history><susname></susname><ohnedetails></ohnedetails></event>
<event id="31"><start_date>2024-05-21 13:55</start_date><end_date>2024-05-21 14:40</end_date><text>EF05a</text><kommentar></kommentar><klasse>EF05a</klasse><anzeige></anzeige><rasterid_wp></rasterid_wp><readonly>1</readonly><zimmer>97</zimmer><zimmerkuerzel>H21</zimmerkuerzel><lehrer>-2</lehrer><lehrerkuerzelname>Bl&#246;chliger Ivo (Blc)</lehrerkuerzelname><lehrer_kurs>Lehrperson aus Kursverbindung  (Blc)</lehrer_kurs><lehrer_rv></lehrer_rv><reservator>Capaul Urs</reservator><reservation></reservation><istrv>1</istrv><markierung>none</markierung><textdeco></textdeco><color>#77B0D4</color><event_type>0_stp</event_type><show_pru_link>1</show_pru_link><show_abs_link>zentral</show_abs_link><show_haa_link>1</show_haa_link><klassentyp>v</klassentyp><lehrerkuerzel>Blc</lehrerkuerzel><kurskuerzel>EF05a</kurskuerzel><kursid>49964</kursid><kursind>0</kursind><neuerlehrer></neuerlehrer><mandant></mandant><mandantname></mandantname><info1></info1><anzeigestp></anzeigestp><fachkuerzel>IN</fachkuerzel><history></history><susname></susname><ohnedetails></ohnedetails></event>
<event id="32"><start_date>2024-05-17 13:55</start_date><end_date>2024-05-17 14:40</end_date><text>IN-4eNP-Sbt</text><kommentar></kommentar><klasse>4eNP</klasse><anzeige></anzeige><rasterid_wp></rasterid_wp><readonly>1</readonly><zimmer>97</zimmer><zimmerkuerzel>H21</zimmerkuerzel><lehrer>-2</lehrer><lehrerkuerzelname>Schubert Karlheinz (Sbt)</lehrerkuerzelname><lehrer_kurs>Lehrperson aus Kursverbindung  (Sbt)</lehrer_kurs><lehrer_rv></lehrer_rv><reservator>Capaul Urs</reservator><reservation></reservation><istrv>1</istrv><markierung>none</markierung><textdeco></textdeco><color>#77B0D4</color><event_type>0_stp</event_type><show_pru_link>0</show_pru_link><show_abs_link>zentral</show_abs_link><show_haa_link>0</show_haa_link><klassentyp>r</klassentyp><lehrerkuerzel>Sbt</lehrerkuerzel><kurskuerzel>IN-4eNP-Sbt</kurskuerzel><kursid>34679</kursid><kursind></kursind><neuerlehrer></neuerlehrer><mandant></mandant><mandantname></mandantname><info1></info1><anzeigestp></anzeigestp><fachkuerzel>IN</fachkuerzel><history></history><susname></susname><ohnedetails></ohnedetails></event>
<event id="33"><start_date>2024-05-15 13:55</start_date><end_date>2024-05-15 14:40</end_date><text>M-1dNP-Kll</text><kommentar></kommentar><klasse>1dNP</klasse><anzeige></anzeige><rasterid_wp></rasterid_wp><readonly>1</readonly><zimmer>97</zimmer><zimmerkuerzel>H21</zimmerkuerzel><lehrer>-2</lehrer><lehrerkuerzelname>Keller Markus (Kll)</lehrerkuerzelname><lehrer_kurs>Lehrperson aus Kursverbindung  (Kll)</lehrer_kurs><lehrer_rv></lehrer_rv><reservator>Capaul Urs</reservator><reservation></reservation><istrv>1</istrv><markierung>none</markierung><textdeco></textdeco><color>#77B0D4</color><event_type>0_stp</event_type><show_pru_link>0</show_pru_link><show_abs_link>zentral</show_abs_link><show_haa_link>0</show_haa_link><klassentyp>r</klassentyp><lehrerkuerzel>Kll</lehrerkuerzel><kurskuerzel>M-1dNP-Kll</kurskuerzel><kursid>47874</kursid><kursind></kursind><neuerlehrer></neuerlehrer><mandant></mandant><mandantname></mandantname><info1></info1><anzeigestp></anzeigestp><fachkuerzel>M</fachkuerzel><history></history><susname></susname><ohnedetails></ohnedetails></event>
<event id="34"><start_date>2024-05-16 13:55</start_date><end_date>2024-05-16 14:40</end_date><text>M-4lW-Gh</text><kommentar></kommentar><klasse>4lW</klasse><anzeige></anzeige><rasterid_wp></rasterid_wp><readonly>1</readonly><zimmer>97</zimmer><zimmerkuerzel>H21</zimmerkuerzel><lehrer>-2</lehrer><lehrerkuerzelname>Ghobrial Karim (Gh)</lehrerkuerzelname><lehrer_kurs>Lehrperson aus Kursverbindung  (Gh)</lehrer_kurs><lehrer_rv></lehrer_rv><reservator>Capaul Urs</reservator><reservation></reservation><istrv>1</istrv><markierung>none</markierung><textdeco></textdeco><color>#77B0D4</color><event_type>0_stp</event_type><show_pru_link>0</show_pru_link><show_abs_link>zentral</show_abs_link><show_haa_link>0</show_haa_link><klassentyp>r</klassentyp><lehrerkuerzel>Gh</lehrerkuerzel><kurskuerzel>M-4lW-Gh</kurskuerzel><kursid>36882</kursid><kursind></kursind><neuerlehrer></neuerlehrer><mandant></mandant><mandantname></mandantname><info1></info1><anzeigestp></anzeigestp><fachkuerzel>M</fachkuerzel><history></history><susname></susname><ohnedetails></ohnedetails></event>
<event id="35"><start_date>2024-05-13 13:55</start_date><end_date>2024-05-13 14:40</end_date><text>M-4mS*-Kll</text><kommentar></kommentar><klasse>4mS*</klasse><anzeige></anzeige><rasterid_wp></rasterid_wp><readonly>1</readonly><zimmer>97</zimmer><zimmerkuerzel>H21</zimmerkuerzel><lehrer>-2</lehrer><lehrerkuerzelname>Keller Markus (Kll)</lehrerkuerzelname><lehrer_kurs>Lehrperson aus Kursverbindung  (Kll)</lehrer_kurs><lehrer_rv></lehrer_rv><reservator>Capaul Urs</reservator><reservation></reservation><istrv>1</istrv><markierung>none</markierung><textdeco></textdeco><color>#77B0D4</color><event_type>0_stp</event_type><show_pru_link>0</show_pru_link><show_abs_link>zentral</show_abs_link><show_haa_link>0</show_haa_link><klassentyp>r</klassentyp><lehrerkuerzel>Kll</lehrerkuerzel><kurskuerzel>M-4mS*-Kll</kurskuerzel><kursid>36995</kursid><kursind></kursind><neuerlehrer></neuerlehrer><mandant></mandant><mandantname></mandantname><info1></info1><anzeigestp></anzeigestp><fachkuerzel>M</fachkuerzel><history></history><susname></susname><ohnedetails></ohnedetails></event>
<event id="36"><start_date>2024-05-14 14:49</start_date><end_date>2024-05-14 15:34</end_date><text>EF05a</text><kommentar></kommentar><klasse>EF05a</klasse><anzeige></anzeige><rasterid_wp></rasterid_wp><readonly>1</readonly><zimmer>97</zimmer><zimmerkuerzel>H21</zimmerkuerzel><lehrer>-2</lehrer><lehrerkuerzelname>Bl&#246;chliger Ivo (Blc)</lehrerkuerzelname><lehrer_kurs>Lehrperson aus Kursverbindung  (Blc)</lehrer_kurs><lehrer_rv></lehrer_rv><reservator>Capaul Urs</reservator><reservation></reservation><istrv>1</istrv><markierung>none</markierung><textdeco></textdeco><color>#77B0D4</color><event_type>0_stp</event_type><show_pru_link>1</show_pru_link><show_abs_link>zentral</show_abs_link><show_haa_link>1</show_haa_link><klassentyp>v</klassentyp><lehrerkuerzel>Blc</lehrerkuerzel><kurskuerzel>EF05a</kurskuerzel><kursid>49964</kursid><kursind>0</kursind><neuerlehrer></neuerlehrer><mandant></mandant><mandantname></mandantname><info1></info1><anzeigestp></anzeigestp><fachkuerzel>IN</fachkuerzel><history></history><susname></susname><ohnedetails></ohnedetails></event>
<event id="37"><start_date>2024-05-21 14:49</start_date><end_date>2024-05-21 15:34</end_date><text>EF05a</text><kommentar></kommentar><klasse>EF05a</klasse><anzeige></anzeige><rasterid_wp></rasterid_wp><readonly>1</readonly><zimmer>97</zimmer><zimmerkuerzel>H21</zimmerkuerzel><lehrer>-2</lehrer><lehrerkuerzelname>Bl&#246;chliger Ivo (Blc)</lehrerkuerzelname><lehrer_kurs>Lehrperson aus Kursverbindung  (Blc)</lehrer_kurs><lehrer_rv></lehrer_rv><reservator>Capaul Urs</reservator><reservation></reservation><istrv>1</istrv><markierung>none</markierung><textdeco></textdeco><color>#77B0D4</color><event_type>0_stp</event_type><show_pru_link>1</show_pru_link><show_abs_link>zentral</show_abs_link><show_haa_link>1</show_haa_link><klassentyp>v</klassentyp><lehrerkuerzel>Blc</lehrerkuerzel><kurskuerzel>EF05a</kurskuerzel><kursid>49964</kursid><kursind>0</kursind><neuerlehrer></neuerlehrer><mandant></mandant><mandantname></mandantname><info1></info1><anzeigestp></anzeigestp><fachkuerzel>IN</fachkuerzel><history></history><susname></susname><ohnedetails></ohnedetails></event>
<event id="38"><start_date>2024-05-17 14:49</start_date><end_date>2024-05-17 15:34</end_date><text>IN-4eNP-Sbt</text><kommentar></kommentar><klasse>4eNP</klasse><anzeige></anzeige><rasterid_wp></rasterid_wp><readonly>1</readonly><zimmer>97</zimmer><zimmerkuerzel>H21</zimmerkuerzel><lehrer>-2</lehrer><lehrerkuerzelname>Schubert Karlheinz (Sbt)</lehrerkuerzelname><lehrer_kurs>Lehrperson aus Kursverbindung  (Sbt)</lehrer_kurs><lehrer_rv></lehrer_rv><reservator>Capaul Urs</reservator><reservation></reservation><istrv>1</istrv><markierung>none</markierung><textdeco></textdeco><color>#77B0D4</color><event_type>0_stp</event_type><show_pru_link>0</show_pru_link><show_abs_link>zentral</show_abs_link><show_haa_link>0</show_haa_link><klassentyp>r</klassentyp><lehrerkuerzel>Sbt</lehrerkuerzel><kurskuerzel>IN-4eNP-Sbt</kurskuerzel><kursid>34679</kursid><kursind></kursind><neuerlehrer></neuerlehrer><mandant></mandant><mandantname></mandantname><info1></info1><anzeigestp></anzeigestp><fachkuerzel>IN</fachkuerzel><history></history><susname></susname><ohnedetails></ohnedetails></event>
<event id="39"><start_date>2024-05-15 14:49</start_date><end_date>2024-05-15 15:34</end_date><text>M-1dNP-Kll</text><kommentar></kommentar><klasse>1dNP</klasse><anzeige></anzeige><rasterid_wp></rasterid_wp><readonly>1</readonly><zimmer>97</zimmer><zimmerkuerzel>H21</zimmerkuerzel><lehrer>-2</lehrer><lehrerkuerzelname>Keller Markus (Kll)</lehrerkuerzelname><lehrer_kurs>Lehrperson aus Kursverbindung  (Kll)</lehrer_kurs><lehrer_rv></lehrer_rv><reservator>Capaul Urs</reservator><reservation></reservation><istrv>1</istrv><markierung>none</markierung><textdeco></textdeco><color>#77B0D4</color><event_type>0_stp</event_type><show_pru_link>0</show_pru_link><show_abs_link>zentral</show_abs_link><show_haa_link>0</show_haa_link><klassentyp>r</klassentyp><lehrerkuerzel>Kll</lehrerkuerzel><kurskuerzel>M-1dNP-Kll</kurskuerzel><kursid>47874</kursid><kursind></kursind><neuerlehrer></neuerlehrer><mandant></mandant><mandantname></mandantname><info1></info1><anzeigestp></anzeigestp><fachkuerzel>M</fachkuerzel><history></history><susname></susname><ohnedetails></ohnedetails></event>
<event id="40"><start_date>2024-05-13 14:49</start_date><end_date>2024-05-13 15:34</end_date><text>M-4mS*-Kll</text><kommentar></kommentar><klasse>4mS*</klasse><anzeige></anzeige><rasterid_wp></rasterid_wp><readonly>1</readonly><zimmer>97</zimmer><zimmerkuerzel>H21</zimmerkuerzel><lehrer>-2</lehrer><lehrerkuerzelname>Keller Markus (Kll)</lehrerkuerzelname><lehrer_kurs>Lehrperson aus Kursverbindung  (Kll)</lehrer_kurs><lehrer_rv></lehrer_rv><reservator>Capaul Urs</reservator><reservation></reservation><istrv>1</istrv><markierung>none</markierung><textdeco></textdeco><color>#77B0D4</color><event_type>0_stp</event_type><show_pru_link>0</show_pru_link><show_abs_link>zentral</show_abs_link><show_haa_link>0</show_haa_link><klassentyp>r</klassentyp><lehrerkuerzel>Kll</lehrerkuerzel><kurskuerzel>M-4mS*-Kll</kurskuerzel><kursid>36995</kursid><kursind></kursind><neuerlehrer></neuerlehrer><mandant></mandant><mandantname></mandantname><info1></info1><anzeigestp></anzeigestp><fachkuerzel>M</fachkuerzel><history></history><susname></susname><ohnedetails></ohnedetails></event>
<event id="41"><start_date>2024-05-17 15:43</start_date><end_date>2024-05-17 16:28</end_date><text>IN-2mSM-Sbt</text><kommentar></kommentar><klasse>2mSM</klasse><anzeige></anzeige><rasterid_wp></rasterid_wp><readonly>1</readonly><zimmer>97</zimmer><zimmerkuerzel>H21</zimmerkuerzel><lehrer>-2</lehrer><lehrerkuerzelname>Schubert Karlheinz (Sbt)</lehrerkuerzelname><lehrer_kurs>Lehrperson aus Kursverbindung  (Sbt)</lehrer_kurs><lehrer_rv></lehrer_rv><reservator>Capaul Urs</reservator><reservation></reservation><istrv>1</istrv><markierung>none</markierung><textdeco></textdeco><color>#77B0D4</color><event_type>0_stp</event_type><show_pru_link>0</show_pru_link><show_abs_link>zentral</show_abs_link><show_haa_link>0</show_haa_link><klassentyp>r</klassentyp><lehrerkuerzel>Sbt</lehrerkuerzel><kurskuerzel>IN-2mSM-Sbt</kurskuerzel><kursid>46678</kursid><kursind></kursind><neuerlehrer></neuerlehrer><mandant></mandant><mandantname></mandantname><info1></info1><anzeigestp></anzeigestp><fachkuerzel>IN</fachkuerzel><history></history><susname></susname><ohnedetails></ohnedetails></event>
<event id="42"><start_date>2024-05-13 15:43</start_date><end_date>2024-05-13 16:28</end_date><text>IN-4cN**P**-Kll</text><kommentar></kommentar><klasse>4cN**P**</klasse><anzeige></anzeige><rasterid_wp></rasterid_wp><readonly>1</readonly><zimmer>97</zimmer><zimmerkuerzel>H21</zimmerkuerzel><lehrer>-2</lehrer><lehrerkuerzelname>Keller Markus (Kll)</lehrerkuerzelname><lehrer_kurs>Lehrperson aus Kursverbindung  (Kll)</lehrer_kurs><lehrer_rv></lehrer_rv><reservator>Capaul Urs</reservator><reservation></reservation><istrv>1</istrv><markierung>none</markierung><textdeco></textdeco><color>#77B0D4</color><event_type>0_stp</event_type><show_pru_link>0</show_pru_link><show_abs_link>zentral</show_abs_link><show_haa_link>0</show_haa_link><klassentyp>r</klassentyp><lehrerkuerzel>Kll</lehrerkuerzel><kurskuerzel>IN-4cN**P**-Kll</kurskuerzel><kursid>34423</kursid><kursind></kursind><neuerlehrer></neuerlehrer><mandant></mandant><mandantname></mandantname><info1></info1><anzeigestp></anzeigestp><fachkuerzel>IN</fachkuerzel><history></history><susname></susname><ohnedetails></ohnedetails></event>
<event id="43"><start_date>2024-05-14 15:43</start_date><end_date>2024-05-14 16:28</end_date><text>M-3hW*-Blc</text><kommentar></kommentar><klasse>3hW*</klasse><anzeige></anzeige><rasterid_wp></rasterid_wp><readonly>1</readonly><zimmer>97</zimmer><zimmerkuerzel>H21</zimmerkuerzel><lehrer>-2</lehrer><lehrerkuerzelname>Bl&#246;chliger Ivo (Blc)</lehrerkuerzelname><lehrer_kurs>Lehrperson aus Kursverbindung  (Blc)</lehrer_kurs><lehrer_rv></lehrer_rv><reservator>Capaul Urs</reservator><reservation></reservation><istrv>1</istrv><markierung>none</markierung><textdeco></textdeco><color>#77B0D4</color><event_type>0_stp</event_type><show_pru_link>1</show_pru_link><show_abs_link>zentral</show_abs_link><show_haa_link>1</show_haa_link><klassentyp>r</klassentyp><lehrerkuerzel>Blc</lehrerkuerzel><kurskuerzel>M-3hW*-Blc</kurskuerzel><kursid>39142</kursid><kursind>3</kursind><neuerlehrer></neuerlehrer><mandant></mandant><mandantname></mandantname><info1></info1><anzeigestp></anzeigestp><fachkuerzel>M</fachkuerzel><history></history><susname></susname><ohnedetails></ohnedetails></event>
<event id="44"><start_date>2024-05-21 15:43</start_date><end_date>2024-05-21 16:28</end_date><text>M-3hW*-Blc</text><kommentar></kommentar><klasse>3hW*</klasse><anzeige></anzeige><rasterid_wp></rasterid_wp><readonly>1</readonly><zimmer>97</zimmer><zimmerkuerzel>H21</zimmerkuerzel><lehrer>-2</lehrer><lehrerkuerzelname>Bl&#246;chliger Ivo (Blc)</lehrerkuerzelname><lehrer_kurs>Lehrperson aus Kursverbindung  (Blc)</lehrer_kurs><lehrer_rv></lehrer_rv><reservator>Capaul Urs</reservator><reservation></reservation><istrv>1</istrv><markierung>none</markierung><textdeco></textdeco><color>#77B0D4</color><event_type>0_stp</event_type><show_pru_link>1</show_pru_link><show_abs_link>zentral</show_abs_link><show_haa_link>1</show_haa_link><klassentyp>r</klassentyp><lehrerkuerzel>Blc</lehrerkuerzel><kurskuerzel>M-3hW*-Blc</kurskuerzel><kursid>39142</kursid><kursind>3</kursind><neuerlehrer></neuerlehrer><mandant></mandant><mandantname></mandantname><info1></info1><anzeigestp></anzeigestp><fachkuerzel>M</fachkuerzel><history></history><susname></susname><ohnedetails></ohnedetails></event>
<event id="45"><start_date>2024-05-17 16:33</start_date><end_date>2024-05-17 17:18</end_date><text>IN-2mSM-Sbt</text><kommentar></kommentar><klasse>2mSM</klasse><anzeige></anzeige><rasterid_wp></rasterid_wp><readonly>1</readonly><zimmer>97</zimmer><zimmerkuerzel>H21</zimmerkuerzel><lehrer>-2</lehrer><lehrerkuerzelname>Schubert Karlheinz (Sbt)</lehrerkuerzelname><lehrer_kurs>Lehrperson aus Kursverbindung  (Sbt)</lehrer_kurs><lehrer_rv></lehrer_rv><reservator>Capaul Urs</reservator><reservation></reservation><istrv>1</istrv><markierung>none</markierung><textdeco></textdeco><color>#77B0D4</color><event_type>0_stp</event_type><show_pru_link>0</show_pru_link><show_abs_link>zentral</show_abs_link><show_haa_link>0</show_haa_link><klassentyp>r</klassentyp><lehrerkuerzel>Sbt</lehrerkuerzel><kurskuerzel>IN-2mSM-Sbt</kurskuerzel><kursid>46678</kursid><kursind></kursind><neuerlehrer></neuerlehrer><mandant></mandant><mandantname></mandantname><info1></info1><anzeigestp></anzeigestp><fachkuerzel>IN</fachkuerzel><history></history><susname></susname><ohnedetails></ohnedetails></event>
<event id="46"><start_date>2024-05-13 16:33</start_date><end_date>2024-05-13 17:18</end_date><text>IN-4cN**P**-Kll</text><kommentar></kommentar><klasse>4cN**P**</klasse><anzeige></anzeige><rasterid_wp></rasterid_wp><readonly>1</readonly><zimmer>97</zimmer><zimmerkuerzel>H21</zimmerkuerzel><lehrer>-2</lehrer><lehrerkuerzelname>Keller Markus (Kll)</lehrerkuerzelname><lehrer_kurs>Lehrperson aus Kursverbindung  (Kll)</lehrer_kurs><lehrer_rv></lehrer_rv><reservator>Capaul Urs</reservator><reservation></reservation><istrv>1</istrv><markierung>none</markierung><textdeco></textdeco><color>#77B0D4</color><event_type>0_stp</event_type><show_pru_link>0</show_pru_link><show_abs_link>zentral</show_abs_link><show_haa_link>0</show_haa_link><klassentyp>r</klassentyp><lehrerkuerzel>Kll</lehrerkuerzel><kurskuerzel>IN-4cN**P**-Kll</kurskuerzel><kursid>34423</kursid><kursind></kursind><neuerlehrer></neuerlehrer><mandant></mandant><mandantname></mandantname><info1></info1><anzeigestp></anzeigestp><fachkuerzel>IN</fachkuerzel><history></history><susname></susname><ohnedetails></ohnedetails></event>
<event id="47"><start_date>2024-05-13 17:23</start_date><end_date>2024-05-13 18:08</end_date><text>ISME Vorbereitungskurs Mathe Vorkurs PH*</text><kommentar>ISME Vorbereitungskurs Mathe Vorkurs PH</kommentar><klasse></klasse><anzeige>EXT </anzeige><rasterid_wp></rasterid_wp><readonly>1</readonly><zimmer>97</zimmer><zimmerkuerzel>H21</zimmerkuerzel><lehrer></lehrer><lehrerkuerzelname>Monn Adrian (Mon)</lehrerkuerzelname><lehrer_kurs>Ohne Lehrpersonenverbindung</lehrer_kurs><lehrer_rv></lehrer_rv><reservator>Giger Bea</reservator><reservation>1</reservation><istrv>1</istrv><markierung>12</markierung><textdeco></textdeco><color>#8AB4F7</color><event_type>0_stp</event_type><show_pru_link>0</show_pru_link><show_abs_link>zentral</show_abs_link><show_haa_link>0</show_haa_link><klassentyp></klassentyp><lehrerkuerzel>Mon</lehrerkuerzel><kurskuerzel>Reserviert</kurskuerzel><kursid></kursid><kursind></kursind><neuerlehrer>Mon</neuerlehrer><mandant>EXT0_</mandant><mandantname>isme</mandantname><info1></info1><anzeigestp>ISME Vorbereitungskurs Mathe Vorkurs PH</anzeigestp><fachkuerzel></fachkuerzel><history></history><susname></susname><ohnedetails></ohnedetails></event>
<event id="48"><start_date>2024-05-21 17:23</start_date><end_date>2024-05-21 18:08</end_date><text>ISME Vorbereitungskurs Mathe Vorkurs PH*</text><kommentar>ISME Vorbereitungskurs Mathe Vorkurs PH</kommentar><klasse></klasse><anzeige>EXT </anzeige><rasterid_wp></rasterid_wp><readonly>1</readonly><zimmer>97</zimmer><zimmerkuerzel>H21</zimmerkuerzel><lehrer></lehrer><lehrerkuerzelname>Monn Adrian (Mon)</lehrerkuerzelname><lehrer_kurs>Ohne Lehrpersonenverbindung</lehrer_kurs><lehrer_rv></lehrer_rv><reservator>Giger Bea</reservator><reservation>1</reservation><istrv>1</istrv><markierung>12</markierung><textdeco></textdeco><color>#8AB4F7</color><event_type>0_stp</event_type><show_pru_link>0</show_pru_link><show_abs_link>zentral</show_abs_link><show_haa_link>0</show_haa_link><klassentyp></klassentyp><lehrerkuerzel>Mon</lehrerkuerzel><kurskuerzel>Reserviert</kurskuerzel><kursid></kursid><kursind></kursind><neuerlehrer>Mon</neuerlehrer><mandant>EXT0_</mandant><mandantname>isme</mandantname><info1></info1><anzeigestp>ISME Vorbereitungskurs Mathe Vorkurs PH</anzeigestp><fachkuerzel></fachkuerzel><history></history><susname></susname><ohnedetails></ohnedetails></event>
<event id="49"><start_date>2024-05-13 18:15</start_date><end_date>2024-05-13 19:00</end_date><text>ISME Vorbereitungskurs Mathe Vorkurs PH*</text><kommentar>ISME Vorbereitungskurs Mathe Vorkurs PH</kommentar><klasse></klasse><anzeige>EXT </anzeige><rasterid_wp></rasterid_wp><readonly>1</readonly><zimmer>97</zimmer><zimmerkuerzel>H21</zimmerkuerzel><lehrer></lehrer><lehrerkuerzelname>Monn Adrian (Mon)</lehrerkuerzelname><lehrer_kurs>Ohne Lehrpersonenverbindung</lehrer_kurs><lehrer_rv></lehrer_rv><reservator>Giger Bea</reservator><reservation>1</reservation><istrv>1</istrv><markierung>12</markierung><textdeco></textdeco><color>#8AB4F7</color><event_type>0_stp</event_type><show_pru_link>0</show_pru_link><show_abs_link>zentral</show_abs_link><show_haa_link>0</show_haa_link><klassentyp></klassentyp><lehrerkuerzel>Mon</lehrerkuerzel><kurskuerzel>Reserviert</kurskuerzel><kursid></kursid><kursind></kursind><neuerlehrer>Mon</neuerlehrer><mandant>EXT0_</mandant><mandantname>isme</mandantname><info1></info1><anzeigestp>ISME Vorbereitungskurs Mathe Vorkurs PH</anzeigestp><fachkuerzel></fachkuerzel><history></history><susname></susname><ohnedetails></ohnedetails></event>
<event id="50"><start_date>2024-05-21 18:15</start_date><end_date>2024-05-21 19:00</end_date><text>ISME Vorbereitungskurs Mathe Vorkurs PH*</text><kommentar>ISME Vorbereitungskurs Mathe Vorkurs PH</kommentar><klasse></klasse><anzeige>EXT </anzeige><rasterid_wp></rasterid_wp><readonly>1</readonly><zimmer>97</zimmer><zimmerkuerzel>H21</zimmerkuerzel><lehrer></lehrer><lehrerkuerzelname>Monn Adrian (Mon)</lehrerkuerzelname><lehrer_kurs>Ohne Lehrpersonenverbindung</lehrer_kurs><lehrer_rv></lehrer_rv><reservator>Giger Bea</reservator><reservation>1</reservation><istrv>1</istrv><markierung>12</markierung><textdeco></textdeco><color>#8AB4F7</color><event_type>0_stp</event_type><show_pru_link>0</show_pru_link><show_abs_link>zentral</show_abs_link><show_haa_link>0</show_haa_link><klassentyp></klassentyp><lehrerkuerzel>Mon</lehrerkuerzel><kurskuerzel>Reserviert</kurskuerzel><kursid></kursid><kursind></kursind><neuerlehrer>Mon</neuerlehrer><mandant>EXT0_</mandant><mandantname>isme</mandantname><info1></info1><anzeigestp>ISME Vorbereitungskurs Mathe Vorkurs PH</anzeigestp><fachkuerzel></fachkuerzel><history></history><susname></susname><ohnedetails></ohnedetails></event>
<event id="51"><start_date>2024-05-13 19:05</start_date><end_date>2024-05-13 19:50</end_date><text>ISME Vorbereitungskurs Mathe Vorkurs PH*</text><kommentar>ISME Vorbereitungskurs Mathe Vorkurs PH</kommentar><klasse></klasse><anzeige>EXT </anzeige><rasterid_wp></rasterid_wp><readonly>1</readonly><zimmer>97</zimmer><zimmerkuerzel>H21</zimmerkuerzel><lehrer></lehrer><lehrerkuerzelname>Monn Adrian (Mon)</lehrerkuerzelname><lehrer_kurs>Ohne Lehrpersonenverbindung</lehrer_kurs><lehrer_rv></lehrer_rv><reservator>Giger Bea</reservator><reservation>1</reservation><istrv>1</istrv><markierung>12</markierung><textdeco></textdeco><color>#8AB4F7</color><event_type>0_stp</event_type><show_pru_link>0</show_pru_link><show_abs_link>zentral</show_abs_link><show_haa_link>0</show_haa_link><klassentyp></klassentyp><lehrerkuerzel>Mon</lehrerkuerzel><kurskuerzel>Reserviert</kurskuerzel><kursid></kursid><kursind></kursind><neuerlehrer>Mon</neuerlehrer><mandant>EXT0_</mandant><mandantname>isme</mandantname><info1></info1><anzeigestp>ISME Vorbereitungskurs Mathe Vorkurs PH</anzeigestp><fachkuerzel></fachkuerzel><history></history><susname></susname><ohnedetails></ohnedetails></event>
<event id="52"><start_date>2024-05-21 19:05</start_date><end_date>2024-05-21 19:50</end_date><text>ISME Vorbereitungskurs Mathe Vorkurs PH*</text><kommentar>ISME Vorbereitungskurs Mathe Vorkurs PH</kommentar><klasse></klasse><anzeige>EXT </anzeige><rasterid_wp></rasterid_wp><readonly>1</readonly><zimmer>97</zimmer><zimmerkuerzel>H21</zimmerkuerzel><lehrer></lehrer><lehrerkuerzelname>Monn Adrian (Mon)</lehrerkuerzelname><lehrer_kurs>Ohne Lehrpersonenverbindung</lehrer_kurs><lehrer_rv></lehrer_rv><reservator>Giger Bea</reservator><reservation>1</reservation><istrv>1</istrv><markierung>12</markierung><textdeco></textdeco><color>#8AB4F7</color><event_type>0_stp</event_type><show_pru_link>0</show_pru_link><show_abs_link>zentral</show_abs_link><show_haa_link>0</show_haa_link><klassentyp></klassentyp><lehrerkuerzel>Mon</lehrerkuerzel><kurskuerzel>Reserviert</kurskuerzel><kursid></kursid><kursind></kursind><neuerlehrer>Mon</neuerlehrer><mandant>EXT0_</mandant><mandantname>isme</mandantname><info1></info1><anzeigestp>ISME Vorbereitungskurs Mathe Vorkurs PH</anzeigestp><fachkuerzel></fachkuerzel><history></history><susname></susname><ohnedetails></ohnedetails></event>
<event id="53"><start_date>2024-05-13 19:55</start_date><end_date>2024-05-13 20:40</end_date><text>ISME Vorbereitungskurs Mathe Vorkurs PH*</text><kommentar>ISME Vorbereitungskurs Mathe Vorkurs PH</kommentar><klasse></klasse><anzeige>EXT </anzeige><rasterid_wp></rasterid_wp><readonly>1</readonly><zimmer>97</zimmer><zimmerkuerzel>H21</zimmerkuerzel><lehrer></lehrer><lehrerkuerzelname>Monn Adrian (Mon)</lehrerkuerzelname><lehrer_kurs>Ohne Lehrpersonenverbindung</lehrer_kurs><lehrer_rv></lehrer_rv><reservator>Giger Bea</reservator><reservation>1</reservation><istrv>1</istrv><markierung>12</markierung><textdeco></textdeco><color>#8AB4F7</color><event_type>0_stp</event_type><show_pru_link>0</show_pru_link><show_abs_link>zentral</show_abs_link><show_haa_link>0</show_haa_link><klassentyp></klassentyp><lehrerkuerzel>Mon</lehrerkuerzel><kurskuerzel>Reserviert</kurskuerzel><kursid></kursid><kursind></kursind><neuerlehrer>Mon</neuerlehrer><mandant>EXT0_</mandant><mandantname>isme</mandantname><info1></info1><anzeigestp>ISME Vorbereitungskurs Mathe Vorkurs PH</anzeigestp><fachkuerzel></fachkuerzel><history></history><susname></susname><ohnedetails></ohnedetails></event>
<event id="54"><start_date>2024-05-21 19:55</start_date><end_date>2024-05-21 20:40</end_date><text>ISME Vorbereitungskurs Mathe Vorkurs PH*</text><kommentar>ISME Vorbereitungskurs Mathe Vorkurs PH</kommentar><klasse></klasse><anzeige>EXT </anzeige><rasterid_wp></rasterid_wp><readonly>1</readonly><zimmer>97</zimmer><zimmerkuerzel>H21</zimmerkuerzel><lehrer></lehrer><lehrerkuerzelname>Monn Adrian (Mon)</lehrerkuerzelname><lehrer_kurs>Ohne Lehrpersonenverbindung</lehrer_kurs><lehrer_rv></lehrer_rv><reservator>Giger Bea</reservator><reservation>1</reservation><istrv>1</istrv><markierung>12</markierung><textdeco></textdeco><color>#8AB4F7</color><event_type>0_stp</event_type><show_pru_link>0</show_pru_link><show_abs_link>zentral</show_abs_link><show_haa_link>0</show_haa_link><klassentyp></klassentyp><lehrerkuerzel>Mon</lehrerkuerzel><kurskuerzel>Reserviert</kurskuerzel><kursid></kursid><kursind></kursind><neuerlehrer>Mon</neuerlehrer><mandant>EXT0_</mandant><mandantname>isme</mandantname><info1></info1><anzeigestp>ISME Vorbereitungskurs Mathe Vorkurs PH</anzeigestp><fachkuerzel></fachkuerzel><history></history><susname></susname><ohnedetails></ohnedetails></event>
</data>